[
  {
    "model_manuf": "发布日期",
    "model_model": "2022 5.15",
    "model_name_manuf": "信息",
    "model_name_model": "版本号:8"
  },
  {
    "model_manuf": "发布日期",
    "model_model": "2022 5.15",
    "model_name_manuf": "信息",
    "model_name_model": "酷安@娄攵石马闲耳卯立占"
  },
  {
    "model_manuf": "Everest",
    "model_model": "8848 M3",
    "model_name_manuf": "8848",
    "model_name_model": "8848 钛金手机M3"
  },
  {
    "model_manuf": "HONOR",
    "model_model": "MGI-AN00",
    "model_name_manuf": "荣耀/非华为",
    "model_name_model": "荣耀 Magic V"
  },
  {
    "model_manuf": "HONOR",
    "model_model": "TFY-AN40",
    "model_name_manuf": "荣耀/非华为",
    "model_name_model": "荣耀 Play 6 T Pro"
  },
  {
    "model_manuf": "HONOR",
    "model_model": "CMA-AN40",
    "model_name_manuf": "荣耀/非华为",
    "model_name_model": "荣耀 Play 6 T"
  },
  {
    "model_manuf": "HONOR",
    "model_model": "LGE-AN00",
    "model_name_manuf": "荣耀/非华为",
    "model_name_model": "荣耀 Magic4"
  },
  {
    "model_manuf": "HONOR",
    "model_model": "LGE-AN10",
    "model_name_manuf": "荣耀/非华为",
    "model_name_model": "荣耀 Magic4 Pro"
  },
  {
    "model_manuf": "HONOR",
    "model_model": "LGE-AN20",
    "model_name_manuf": "荣耀/非华为",
    "model_name_model": "荣耀 Magic4 至臻版"
  },
  {
    "model_manuf": "HONOR",
    "model_model": "ELZ-AN20",
    "model_name_manuf": "荣耀/非华为",
    "model_name_model": "荣耀 Magic3 至臻版"
  },
  {
    "model_manuf": "HONOR",
    "model_model": "ELZ-AN10",
    "model_name_manuf": "荣耀/非华为",
    "model_name_model": "荣耀 Magic3 Pro"
  },
  {
    "model_manuf": "HONOR",
    "model_model": "ELZ-AN00",
    "model_name_manuf": "荣耀/非华为",
    "model_name_model": "荣耀 Magic3"
  },
  {
    "model_manuf": "HONOR",
    "model_model": "TNA-AN00",
    "model_name_manuf": "荣耀/非华为",
    "model_name_model": "荣耀 60 Pro"
  },
  {
    "model_manuf": "HONOR",
    "model_model": "LSA-AN00",
    "model_name_manuf": "荣耀/非华为",
    "model_name_model": "荣耀 60"
  },
  {
    "model_manuf": "HONOR",
    "model_model": "GIA-AN00",
    "model_name_manuf": "荣耀/非华为",
    "model_name_model": "荣耀 60 SE"
  },
  {
    "model_manuf": "HONOR",
    "model_model": "RNA-AN00",
    "model_name_manuf": "荣耀/非华为",
    "model_name_model": "荣耀 50 Pro"
  },
  {
    "model_manuf": "HONOR",
    "model_model": "NTH-AN00",
    "model_name_manuf": "荣耀/非华为",
    "model_name_model": "荣耀 50"
  },
  {
    "model_manuf": "HONOR",
    "model_model": "JLH-AN00",
    "model_name_manuf": "荣耀/非华为",
    "model_name_model": "荣耀 50 SE"
  },
  {
    "model_manuf": "HUAWEI",
    "model_model": "TET-AN50",
    "model_name_manuf": "华为",
    "model_name_model": "华为 Mate X2 典藏版"
  },
  {
    "model_manuf": "HUAWEI",
    "model_model": "TET-AN00",
    "model_name_manuf": "华为",
    "model_name_model": "华为 Mate X2 5G"
  },
  {
    "model_manuf": "HUAWEI",
    "model_model": "TET-AN10",
    "model_name_manuf": "华为",
    "model_name_model": "华为 Mate X2 4G"
  },
  {
    "model_manuf": "HUAWEI",
    "model_model": "JAD-AL00",
    "model_name_manuf": "华为",
    "model_name_model": "华为 P50 Pro 骁龙版"
  },
  {
    "model_manuf": "HUAWEI",
    "model_model": "JAD-AL50",
    "model_name_manuf": "华为",
    "model_name_model": "华为 P50 Pro 麒麟版"
  },
  {
    "model_manuf": "HUAWEI",
    "model_model": "ABR-AL00",
    "model_name_manuf": "华为",
    "model_name_model": "华为 P50"
  },
  {
    "model_manuf": "HUAWEI",
    "model_model": "BAL-AL00",
    "model_name_manuf": "华为",
    "model_name_model": "华为 P50 Pocket"
  },
  {
    "model_manuf": "HUAWEI",
    "model_model": "ABR-AL60",
    "model_name_manuf": "华为",
    "model_name_model": "华为 P50E"
  },
  {
    "model_manuf": "HUAWEI",
    "model_model": "ELS-AN10",
    "model_name_manuf": "华为",
    "model_name_model": "华为 P40 Pro+"
  },
  {
    "model_manuf": "HUAWEI",
    "model_model": "ELS-AN00",
    "model_name_manuf": "华为",
    "model_name_model": "华为 P40 Pro"
  },
  {
    "model_manuf": "HUAWEI",
    "model_model": "ANA-AN00",
    "model_name_manuf": "华为",
    "model_name_model": "华为 P40"
  },
  {
    "model_manuf": "HUAWEI",
    "model_model": "VOG-AL10",
    "model_name_manuf": "华为",
    "model_name_model": "华为 P30 Pro"
  },
  {
    "model_manuf": "HUAWEI",
    "model_model": "ELE-AL00",
    "model_name_manuf": "华为",
    "model_name_model": "华为 P30"
  },
  {
    "model_manuf": "HUAWEI",
    "model_model": "RTE-AL00",
    "model_name_manuf": "华为",
    "model_name_model": "华为 Nova 9 Pro"
  },
  {
    "model_manuf": "HUAWEI",
    "model_model": "NAM-AL00",
    "model_name_manuf": "华为",
    "model_name_model": "华为 Nova 9"
  },
  {
    "model_manuf": "HUAWEI",
    "model_model": "JLN-AL00",
    "model_name_manuf": "华为",
    "model_name_model": "华为 Nova 9 SE"
  },
  {
    "model_manuf": "HUAWEI",
    "model_model": "BRQ-AN00",
    "model_name_manuf": "华为",
    "model_name_model": "华为 Nova 8 Pro"
  },
  {
    "model_manuf": "HUAWEI",
    "model_model": "ANG-AN00",
    "model_name_manuf": "华为",
    "model_name_model": "华为 Nova 8"
  },
  {
    "model_manuf": "HUAWEI",
    "model_model": "JSC-AL50",
    "model_name_manuf": "华为",
    "model_name_model": "华为 Nova 8 SE"
  },
  {
    "model_manuf": "HUAWEI",
    "model_model": "ANG-AN00",
    "model_name_manuf": "华为",
    "model_name_model": "华为 Nova 8"
  },
  {
    "model_manuf": "HUAWEI",
    "model_model": "ATH-AL00",
    "model_name_manuf": "华为",
    "model_name_model": "荣耀7i"
  },
  {
    "model_manuf": "HUAWEI",
    "model_model": "H60-L21",
    "model_name_manuf": "华为",
    "model_name_model": "荣耀6至尊版"
  },
  {
    "model_manuf": "HUAWEI",
    "model_model": "PE-TL10",
    "model_name_manuf": "华为",
    "model_name_model": "荣耀6 Plus"
  },
  {
    "model_manuf": "HUAWEI",
    "model_model": "VTR-AL00",
    "model_name_manuf": "华为",
    "model_name_model": "P10"
  },
  {
    "model_manuf": "HUAWEI",
    "model_model": "VKY-AL00",
    "model_name_manuf": "华为",
    "model_name_model": "P10 Plus"
  },
  {
    "model_manuf": "HUAWEI",
    "model_model": "KNT-AL10",
    "model_name_manuf": "华为",
    "model_name_model": "荣耀 V8"
  },
  {
    "model_manuf": "HUAWEI",
    "model_model": "EVA-AL00",
    "model_name_manuf": "华为",
    "model_name_model": "P9"
  },
  {
    "model_manuf": "HUAWEI",
    "model_model": "VIE-AL10",
    "model_name_manuf": "华为",
    "model_name_model": "P9 Plus"
  },
  {
    "model_manuf": "HUAWEI",
    "model_model": "HUAWEI CAZ-AL00",
    "model_name_manuf": "华为",
    "model_name_model": "Nova"
  },
  {
    "model_manuf": "HUAWEI",
    "model_model": "MHA-AL00",
    "model_name_manuf": "华为",
    "model_name_model": "Mate 9"
  },
  {
    "model_manuf": "HUAWEI",
    "model_model": "LON-AL00",
    "model_name_manuf": "华为",
    "model_name_model": "Mate 9 Pro"
  },
  {
    "model_manuf": "HUAWEI",
    "model_model": "NTS-AL00",
    "model_name_manuf": "华为",
    "model_name_model": "荣耀 Magic"
  },
  {
    "model_manuf": "HUAWEI",
    "model_model": "LON-AL00-PD",
    "model_name_manuf": "华为",
    "model_name_model": "Mate 9 Porsche Design"
  },
  {
    "model_manuf": "HUAWEI",
    "model_model": "VTR-AL00",
    "model_name_manuf": "华为",
    "model_name_model": "P10"
  },
  {
    "model_manuf": "HUAWEI",
    "model_model": "VKY-AL00",
    "model_name_manuf": "华为",
    "model_name_model": "P10 Plus"
  },
  {
    "model_manuf": "Lenovo",
    "model_model": "Lenovo L71061",
    "model_name_manuf": "联想",
    "model_name_model": "联想拯救者Y90"
  },
  {
    "model_manuf": "Lenovo",
    "model_model": "Lenovo K30-T",
    "model_name_manuf": "联想",
    "model_name_model": "联想K3"
  },
  {
    "model_manuf": "LeMobile",
    "model_model": "Le X620",
    "model_name_manuf": "乐视",
    "model_name_model": "乐视2"
  },
  {
    "model_manuf": "LeMobile",
    "model_model": "Le X525",
    "model_name_manuf": "乐视",
    "model_name_model": "乐视2 Pro"
  },
  {
    "model_manuf": "Letv",
    "model_model": "X600",
    "model_name_manuf": "乐视",
    "model_name_model": "乐视1"
  },
  {
    "model_manuf": "Letv",
    "model_model": "X800+",
    "model_name_manuf": "乐视",
    "model_name_model": "乐视1 Pro"
  },
  {
    "model_manuf": "Letv",
    "model_model": "Letv X500",
    "model_name_manuf": "乐视",
    "model_name_model": "乐视1 S"
  },
  {
    "model_manuf": "Letv",
    "model_model": "Letv X501",
    "model_name_manuf": "乐视",
    "model_name_model": "乐视1 S 太子妃版"
  },
  {
    "model_manuf": "HTC",
    "model_model": "HTC M9e",
    "model_name_manuf": "HTC",
    "model_name_model": "HTC One M9"
  },
  {
    "model_manuf": "HTC",
    "model_model": "HTC One A9",
    "model_name_manuf": "HTC",
    "model_name_model": "HTC One A9"
  },
  {
    "model_manuf": "OPPO",
    "model_model": "OPD2101",
    "model_name_manuf": "OPPO",
    "model_name_model": "OPPO Pad"
  },
  {
    "model_manuf": "OPPO",
    "model_model": "PESM10",
    "model_name_manuf": "OPPO",
    "model_name_model": "OPPO A36"
  },
  {
    "model_manuf": "OPPO",
    "model_model": "PFUM10",
    "model_name_manuf": "OPPO",
    "model_name_model": "OPPO A96"
  },
  {
    "model_manuf": "OPPO",
    "model_model": "PGJM10",
    "model_name_manuf": "OPPO",
    "model_name_model": "OPPO K10"
  },
  {
    "model_manuf": "OPPO",
    "model_model": "PGIM10",
    "model_name_manuf": "OPPO",
    "model_name_model": "OPPO K10 Pro"
  },
  {
    "model_manuf": "OPPO",
    "model_model": "PGCM10",
    "model_name_manuf": "OPPO",
    "model_name_model": "OPPO K9x"
  },
  {
    "model_manuf": "OPPO",
    "model_model": "PEUM00",
    "model_name_manuf": "OPPO",
    "model_name_model": "OPPO Find N"
  },
  {
    "model_manuf": "OPPO",
    "model_model": "PFDM00",
    "model_name_manuf": "OPPO",
    "model_name_model": "OPPO Reno7 Pro"
  },
  {
    "model_manuf": "OPPO",
    "model_model": "PFJM10",
    "model_name_manuf": "OPPO",
    "model_name_model": "OPPO Reno7"
  },
  {
    "model_manuf": "OPPO",
    "model_model": "PFCM00",
    "model_name_manuf": "OPPO",
    "model_name_model": "OPPO Reno7 SE"
  },
  {
    "model_manuf": "OPPO",
    "model_model": "PFVM10",
    "model_name_manuf": "OPPO",
    "model_name_model": "OPPO A56"
  },
  {
    "model_manuf": "OPPO",
    "model_model": "PERM10",
    "model_name_manuf": "OPPO",
    "model_name_model": "OPPO K9s"
  },
  {
    "model_manuf": "OPPO",
    "model_model": "PEYM00",
    "model_name_manuf": "OPPO",
    "model_name_model": "OPPO K9 Pro"
  },
  {
    "model_manuf": "OPPO",
    "model_model": "PFGM00",
    "model_name_manuf": "OPPO",
    "model_name_model": "OPPO A93s"
  },
  {
    "model_manuf": "OPPO",
    "model_model": "PENM00",
    "model_name_manuf": "OPPO",
    "model_name_model": "OPPO Reno6 Pro+"
  },
  {
    "model_manuf": "OPPO",
    "model_model": "PEPM00",
    "model_name_manuf": "OPPO",
    "model_name_model": "OPPO Reno6 Pro"
  },
  {
    "model_manuf": "OPPO",
    "model_model": "PEXM00",
    "model_name_manuf": "OPPO",
    "model_name_model": "OPPO K9"
  },
  {
    "model_manuf": "OPPO",
    "model_model": "PELM00",
    "model_name_manuf": "OPPO",
    "model_name_model": "OPPO A95"
  },
  {
    "model_manuf": "OPPO",
    "model_model": "PEFM00",
    "model_name_manuf": "OPPO",
    "model_name_model": "OPPO A35"
  },
  {
    "model_manuf": "OPPO",
    "model_model": "PEEM00",
    "model_name_manuf": "OPPO",
    "model_name_model": "OPPO Find X3 Pro"
  },
  {
    "model_manuf": "OPPO",
    "model_model": "PEDM00",
    "model_name_manuf": "OPPO",
    "model_name_model": "OPPO Find X3"
  },
  {
    "model_manuf": "OPPO",
    "model_model": "PDRM00",
    "model_name_manuf": "OPPO",
    "model_name_model": "OPPO Reno5 Pro+"
  },
  {
    "model_manuf": "OPPO",
    "model_model": "PDSM00",
    "model_name_manuf": "OPPO",
    "model_name_model": "OPPO Reno5 Pro"
  },
  {
    "model_manuf": "OPPO",
    "model_model": "PEGM00",
    "model_name_manuf": "OPPO",
    "model_name_model": "OPPO Reno5"
  },
  {
    "model_manuf": "OPPO",
    "model_model": "PEGM10",
    "model_name_manuf": "OPPO",
    "model_name_model": "OPPO Reno5K"
  },
  {
    "model_manuf": "OPPO",
    "model_model": "PEMM20",
    "model_name_manuf": "OPPO",
    "model_name_model": "OPPO A55"
  },
  {
    "model_manuf": "OPPO",
    "model_model": "PEHM00",
    "model_name_manuf": "OPPO",
    "model_name_model": "OPPO A93"
  },
  {
    "model_manuf": "OPPO",
    "model_model": "OPPO R9m",
    "model_name_manuf": "OPPO",
    "model_name_model": "OPPO R9"
  },
  {
    "model_manuf": "OPPO",
    "model_model": "x9007",
    "model_name_manuf": "OPPO",
    "model_name_model": "OPPO Find7"
  },
  {
    "model_manuf": "OPPO",
    "model_model": "x909t",
    "model_name_manuf": "OPPO",
    "model_name_model": "OPPO Find5"
  },
  {
    "model_manuf": "OPPO",
    "model_model": "OPPO R7",
    "model_name_manuf": "OPPO",
    "model_name_model": "OPPO R7"
  },
  {
    "model_manuf": "OPPO",
    "model_model": "OPPO R7S",
    "model_name_manuf": "OPPO",
    "model_name_model": "OPPO R7S"
  },
  {
    "model_manuf": "OPPO",
    "model_model": "OPPO R9s Plus",
    "model_name_manuf": "OPPO",
    "model_name_model": "OPPO R9s Plus"
  },
  {
    "model_manuf": "OPPO",
    "model_model": "OPPO R11",
    "model_name_manuf": "OPPO",
    "model_name_model": "OPPO R11"
  },
  {
    "model_manuf": "OPPO",
    "model_model": "OPPO R11 Plus",
    "model_name_manuf": "OPPO",
    "model_name_model": "OPPO R11 Plus"
  },
  {
    "model_manuf": "Smartisan",
    "model_model": "SM705",
    "model_name_manuf": "锤子",
    "model_name_model": "锤子 T1"
  },
  {
    "model_manuf": "Smartisan",
    "model_model": "SM801",
    "model_name_manuf": "锤子",
    "model_name_model": "锤子 T2"
  },
  {
    "model_manuf": "Smartisan",
    "model_model": "YQ601",
    "model_name_manuf": "锤子",
    "model_name_model": "坚果"
  },
  {
    "model_manuf": "Smartisan",
    "model_model": "SM901",
    "model_name_manuf": "锤子",
    "model_name_model": "锤子 T3"
  },
  {
    "model_manuf": "OnePlus",
    "model_model": "A1001",
    "model_name_manuf": "一加",
    "model_name_model": "一加手机1"
  },
  {
    "model_manuf": "OnePlus",
    "model_model": "ONE A2001",
    "model_name_manuf": "一加",
    "model_name_model": "一加手机2"
  },
  {
    "model_manuf": "OnePlus",
    "model_model": "OnePlus A3000",
    "model_name_manuf": "一加",
    "model_name_model": "一加手机3"
  },
  {
    "model_manuf": "OnePlus",
    "model_model": "ONEPLUS A3010",
    "model_name_manuf": "一加",
    "model_name_model": "一加手机3T"
  },
  {
    "model_manuf": "OnePlus",
    "model_model": "A5000",
    "model_name_manuf": "一加",
    "model_name_model": "一加手机5"
  },
  {
    "model_manuf": "ZTE",
    "model_model": "ZTE A2023H",
    "model_name_manuf": "中兴",
    "model_name_model": "中兴 AXON 40"
  },
  {
    "model_manuf": "ZTE",
    "model_model": "ZTE A2023",
    "model_name_manuf": "中兴",
    "model_name_model": "中兴 AXON 40 Pro"
  },
  {
    "model_manuf": "ZTE",
    "model_model": "ZTE A2023P",
    "model_name_manuf": "中兴",
    "model_name_model": "中兴 AXON 40 Ultra"
  },
  {
    "model_manuf": "ZTE",
    "model_model": "ZTE A2022P",
    "model_name_manuf": "中兴",
    "model_name_model": "中兴 AXON 30 Ultra"
  },
  {
    "model_manuf": "ZTE",
    "model_model": "ZTE A2022H",
    "model_name_manuf": "中兴",
    "model_name_model": "中兴 AXON 31 Pro"
  },
  {
    "model_manuf": "ZTE",
    "model_model": "ZTE A2022",
    "model_name_manuf": "中兴",
    "model_name_model": "中兴 AXON 30 Pro"
  },
  {
    "model_manuf": "ZTE",
    "model_model": "ZTE A2322",
    "model_name_manuf": "中兴",
    "model_name_model": "中兴 AXON 30"
  },
  {
    "model_manuf": "ZTE",
    "model_model": "ZTE A2121",
    "model_name_manuf": "中兴",
    "model_name_model": "中兴 AXON 20"
  },
  {
    "model_manuf": "ZTE",
    "model_model": "ZTE A2021",
    "model_name_manuf": "中兴",
    "model_name_model": "中兴 AXON 11 5G"
  },
  {
    "model_manuf": "ZTE",
    "model_model": "ZTE A2020Pro",
    "model_name_manuf": "中兴",
    "model_name_model": "中兴 AXON 10 Pro"
  },
  {
    "model_manuf": "ZTE",
    "model_model": "ZTE C2016",
    "model_name_manuf": "中兴",
    "model_name_model": "中兴 AXON 天机 MAX"
  },
  {
    "model_manuf": "ZTE",
    "model_model": "ZTE B2015",
    "model_name_manuf": "中兴",
    "model_name_model": "中兴 AXON 天机 MINI"
  },
  {
    "model_manuf": "ZTE",
    "model_model": "ZTE A2015",
    "model_name_manuf": "中兴",
    "model_name_model": "中兴 AXON 天机"
  },
  {
    "model_manuf": "ZTE",
    "model_model": "ZTE G720C",
    "model_name_manuf": "中兴",
    "model_name_model": "中兴 星星2号"
  },
  {
    "model_manuf": "ZTE",
    "model_model": "NX529J",
    "model_name_manuf": "中兴",
    "model_name_model": "努比亚Z11 mini全网通"
  },
  {
    "model_manuf": "ZTE",
    "model_model": "NX512J",
    "model_name_manuf": "中兴",
    "model_name_model": "努比亚大牛 Z9 Max"
  },
  {
    "model_manuf": "ZTE",
    "model_model": "NX511J",
    "model_name_manuf": "中兴",
    "model_name_model": "努比亚小牛4 Z9 Mini"
  },
  {
    "model_manuf": "ZTE",
    "model_model": "ZTE C880U",
    "model_name_manuf": "中兴",
    "model_name_model": "ZTE国民指纹机BladeA1"
  },
  {
    "model_manuf": "Nubia",
    "model_model": "NX701J",
    "model_name_manuf": "努比亚/红魔",
    "model_name_model": "努比亚 Z40/努比亚 Z40 Pro"
  },
  {
    "model_manuf": "Nubia",
    "model_model": "NX667J",
    "model_name_manuf": "努比亚/红魔",
    "model_name_model": "努比亚 Z30 Pro"
  },
  {
    "model_manuf": "Nubia",
    "model_model": "NX627J",
    "model_name_manuf": "努比亚/红魔",
    "model_name_model": "努比亚 Z20"
  },
  {
    "model_manuf": "Nubia",
    "model_model": "NX709J",
    "model_name_manuf": "努比亚/红魔",
    "model_name_model": "红魔7 Pro"
  },
  {
    "model_manuf": "Nubia",
    "model_model": "NX679J",
    "model_name_manuf": "努比亚/红魔",
    "model_name_model": "红魔7"
  },
  {
    "model_manuf": "Nubia",
    "model_model": "NX669J-S",
    "model_name_manuf": "努比亚/红魔",
    "model_name_model": "红魔6 S Pro"
  },
  {
    "model_manuf": "Nubia",
    "model_model": "NX669J-P",
    "model_name_manuf": "努比亚/红魔",
    "model_name_model": "红魔6 Pro"
  },
  {
    "model_manuf": "Nubia",
    "model_model": "NX666J",
    "model_name_manuf": "努比亚/红魔",
    "model_name_model": "红魔6R"
  },
  {
    "model_manuf": "Nubia",
    "model_model": "NX669J",
    "model_name_manuf": "努比亚/红魔",
    "model_name_model": "红魔6"
  },
  {
    "model_manuf": "Nubia",
    "model_model": "NX659J",
    "model_name_manuf": "努比亚/红魔",
    "model_name_model": "红魔5G/红魔5S"
  },
  {
    "model_manuf": "Nubia",
    "model_model": "NX629J",
    "model_name_manuf": "努比亚/红魔",
    "model_name_model": "红魔3S/红魔3"
  },
  {
    "model_manuf": "Nubia",
    "model_model": "NX619J",
    "model_name_manuf": "努比亚/红魔",
    "model_name_model": "红魔Mars"
  },
  {
    "model_manuf": "Nubia",
    "model_model": "NX609J",
    "model_name_manuf": "努比亚/红魔",
    "model_name_model": "红魔一代"
  },
  {
    "model_manuf": "GREE",
    "model_model": "G0111",
    "model_name_manuf": "格力",
    "model_name_model": "格力手机1"
  },
  {
    "model_manuf": "GREE",
    "model_model": "G0121",
    "model_name_manuf": "格力",
    "model_name_model": "格力手机1s"
  },
  {
    "model_manuf": "GREE",
    "model_model": "G0128",
    "model_name_manuf": "格力",
    "model_name_model": "格力手机2"
  },
  {
    "model_manuf": "Meizu",
    "model_model": "M192Q",
    "model_name_manuf": "魅族",
    "model_name_model": "魅族 18 S Pro"
  },
  {
    "model_manuf": "Meizu",
    "model_model": "M191Q",
    "model_name_manuf": "魅族",
    "model_name_model": "魅族 18 Pro"
  },
  {
    "model_manuf": "Meizu",
    "model_model": "M182Q",
    "model_name_manuf": "魅族",
    "model_name_model": "魅族 18 S"
  },
  {
    "model_manuf": "Meizu",
    "model_model": "M172Q",
    "model_name_manuf": "魅族",
    "model_name_model": "魅族 18X"
  },
  {
    "model_manuf": "Meizu",
    "model_model": "M181Q",
    "model_name_manuf": "魅族",
    "model_name_model": "魅族 18"
  },
  {
    "model_manuf": "Meizu",
    "model_model": "M091Q",
    "model_name_manuf": "魅族",
    "model_name_model": "魅族 17 Pro"
  },
  {
    "model_manuf": "Meizu",
    "model_model": "M081Q",
    "model_name_manuf": "魅族",
    "model_name_model": "魅族 17"
  },
  {
    "model_manuf": "Meizu",
    "model_model": "M973Q",
    "model_name_manuf": "魅族",
    "model_name_model": "魅族 16 S Pro"
  },
  {
    "model_manuf": "Meizu",
    "model_model": "M892Q",
    "model_name_manuf": "魅族",
    "model_name_model": "魅族 16 th Plus"
  },
  {
    "model_manuf": "Meizu",
    "model_model": "M971Q",
    "model_name_manuf": "魅族",
    "model_name_model": "魅族 16 S"
  },
  {
    "model_manuf": "Meizu",
    "model_model": "M928Q",
    "model_name_manuf": "魅族",
    "model_name_model": "魅族 16 T"
  },
  {
    "model_manuf": "Meizu",
    "model_model": "16X",
    "model_name_manuf": "魅族",
    "model_name_model": "魅族 16 X"
  },
  {
    "model_manuf": "Meizu",
    "model_model": "M926Q",
    "model_name_manuf": "魅族",
    "model_name_model": "魅族 16 XS"
  },
  {
    "model_manuf": "Meizu",
    "model_model": "zero",
    "model_name_manuf": "魅族",
    "model_name_model": "魅族 zero"
  },
  {
    "model_manuf": "Meizu",
    "model_model": "M923Q",
    "model_name_manuf": "魅族",
    "model_name_model": "魅族 Note9"
  },
  {
    "model_manuf": "Meizu",
    "model_model": "M822Q",
    "model_name_manuf": "魅族",
    "model_name_model": "魅族 Note8"
  },
  {
    "model_manuf": "Meizu",
    "model_model": "M852Q",
    "model_name_manuf": "魅族",
    "model_name_model": "魅族 X8"
  },
  {
    "model_manuf": "Meizu",
    "model_model": "MX2",
    "model_name_manuf": "魅族",
    "model_name_model": "MX2"
  },
  {
    "model_manuf": "Meizu",
    "model_model": "M355",
    "model_name_manuf": "魅族",
    "model_name_model": "MX3"
  },
  {
    "model_manuf": "Meizu",
    "model_model": "MX4",
    "model_name_manuf": "魅族",
    "model_name_model": "MX4"
  },
  {
    "model_manuf": "Meizu",
    "model_model": "MX4 Pro",
    "model_name_manuf": "魅族",
    "model_name_model": "MX4 Pro"
  },
  {
    "model_manuf": "Meizu",
    "model_model": "M575M",
    "model_name_manuf": "魅族",
    "model_name_model": "MX5"
  },
  {
    "model_manuf": "Meizu",
    "model_model": "PRO 6",
    "model_name_manuf": "魅族",
    "model_name_model": "PRO 6"
  },
  {
    "model_manuf": "Meizu",
    "model_model": "魅蓝3",
    "model_name_manuf": "魅族",
    "model_name_model": "魅蓝3"
  },
  {
    "model_manuf": "Meizu",
    "model_model": "m1 note",
    "model_name_manuf": "魅族",
    "model_name_model": "魅蓝 note"
  },
  {
    "model_manuf": "Meizu",
    "model_model": "m3 note",
    "model_name_manuf": "魅族",
    "model_name_model": "魅蓝3 note"
  },
  {
    "model_manuf": "Meizu",
    "model_model": "m1 metal",
    "model_name_manuf": "魅族",
    "model_name_model": "魅蓝metal"
  },
  {
    "model_manuf": "Samsung",
    "model_model": "SM-S9080",
    "model_name_manuf": "三星",
    "model_name_model": "Samsung Galaxy S22 Ultra"
  },
  {
    "model_manuf": "Samsung",
    "model_model": "SM-S9060",
    "model_name_manuf": "三星",
    "model_name_model": "Samsung Galaxy S22+"
  },
  {
    "model_manuf": "Samsung",
    "model_model": "SM-S9010",
    "model_name_manuf": "三星",
    "model_name_model": "Samsung Galaxy S22"
  },
  {
    "model_manuf": "Samsung",
    "model_model": "SM-G9980",
    "model_name_manuf": "三星",
    "model_name_model": "Samsung Galaxy S21 Ultra"
  },
  {
    "model_manuf": "Samsung",
    "model_model": "SM-G9960",
    "model_name_manuf": "三星",
    "model_name_model": "Samsung Galaxy S21+"
  },
  {
    "model_manuf": "Samsung",
    "model_model": "SM-G9910",
    "model_name_manuf": "三星",
    "model_name_model": "Samsung Galaxy S22"
  },
  {
    "model_manuf": "Samsung",
    "model_model": "SM-G9880",
    "model_name_manuf": "三星",
    "model_name_model": "Samsung Galaxy S20 Ultra"
  },
  {
    "model_manuf": "Samsung",
    "model_model": "SM-G9860",
    "model_name_manuf": "三星",
    "model_name_model": "Samsung Galaxy S20+"
  },
  {
    "model_manuf": "Samsung",
    "model_model": "SM-G9810",
    "model_name_manuf": "三星",
    "model_name_model": "Samsung Galaxy S20"
  },
  {
    "model_manuf": "Samsung",
    "model_model": "SM-X906C",
    "model_name_manuf": "三星",
    "model_name_model": "Samsung Galaxy Tab S8 Ultra   5G"
  },
  {
    "model_manuf": "Samsung",
    "model_model": "SM-S9080",
    "model_name_manuf": "三星",
    "model_name_model": "Samsung Galaxy Tab S8 Ultra   WIFI"
  },
  {
    "model_manuf": "Samsung",
    "model_model": "SM-X806C",
    "model_name_manuf": "三星",
    "model_name_model": "Samsung Galaxy Tab S8+   5G"
  },
  {
    "model_manuf": "Samsung",
    "model_model": "SM-X800",
    "model_name_manuf": "三星",
    "model_name_model": "Samsung Galaxy Tab S8+   WIFI"
  },
  {
    "model_manuf": "Samsung",
    "model_model": "SM-X706C",
    "model_name_manuf": "三星",
    "model_name_model": "Samsung Galaxy Tab S8   5G"
  },
  {
    "model_manuf": "Samsung",
    "model_model": "SM-X700",
    "model_name_manuf": "三星",
    "model_name_model": "Samsung Galaxy Tab S8   WIFI"
  },
  {
    "model_manuf": "Samsung",
    "model_model": "SM-W2022",
    "model_name_manuf": "三星",
    "model_name_model": "Samsung W22 "
  },
  {
    "model_manuf": "Samsung",
    "model_model": "SM-W2021",
    "model_name_manuf": "三星",
    "model_name_model": "Samsung W21"
  },
  {
    "model_manuf": "Samsung",
    "model_model": "SM-W2020",
    "model_name_manuf": "三星",
    "model_name_model": "Samsung W20"
  },
  {
    "model_manuf": "Samsung",
    "model_model": "SM-W2019",
    "model_name_manuf": "三星",
    "model_name_model": "Samsung W2019"
  },
  {
    "model_manuf": "Samsung",
    "model_model": "SM-W2018",
    "model_name_manuf": "三星",
    "model_name_model": "Samsung W2018"
  },
  {
    "model_manuf": "Samsung",
    "model_model": "SM-F9260",
    "model_name_manuf": "三星",
    "model_name_model": "Samsung Galaxy Z Fold3"
  },
  {
    "model_manuf": "Samsung",
    "model_model": "SM-F9160",
    "model_name_manuf": "三星",
    "model_name_model": "Samsung Galaxy Z Fold2"
  },
  {
    "model_manuf": "Samsung",
    "model_model": "SM-F9000",
    "model_name_manuf": "三星",
    "model_name_model": "Samsung Galaxy Z Fold"
  },
  {
    "model_manuf": "Samsung",
    "model_model": "SM-N9860",
    "model_name_manuf": "三星",
    "model_name_model": "Samsung Galaxy Note20 Ultra"
  },
  {
    "model_manuf": "Samsung",
    "model_model": "SM-N986U",
    "model_name_manuf": "三星",
    "model_name_model": "Samsung Galaxy Note20+"
  },
  {
    "model_manuf": "Samsung",
    "model_model": "SM-N9810",
    "model_name_manuf": "三星",
    "model_name_model": "Samsung Galaxy Note20"
  },
  {
    "model_manuf": "Samsung",
    "model_model": "SM-A5360",
    "model_name_manuf": "三星",
    "model_name_model": "Samsung Galaxy A53"
  },
  {
    "model_manuf": "Samsung",
    "model_model": "SM-G9280",
    "model_name_manuf": "三星",
    "model_name_model": "Galaxy S6 Edge+"
  },
  {
    "model_manuf": "Samsung",
    "model_model": "SM-N9300",
    "model_name_manuf": "三星",
    "model_name_model": "Galaxy Note7"
  },
  {
    "model_manuf": "Samsung",
    "model_model": "SM-G9350",
    "model_name_manuf": "三星",
    "model_name_model": "Galaxy S7 edge"
  },
  {
    "model_manuf": "Samsung",
    "model_model": "SM-G9300",
    "model_name_manuf": "三星",
    "model_name_model": "Galaxy S7"
  },
  {
    "model_manuf": "Samsung",
    "model_model": "SM-G9500",
    "model_name_manuf": "三星",
    "model_name_model": "Galaxy S8"
  },
  {
    "model_manuf": "Samsung",
    "model_model": "SM-G9550",
    "model_name_manuf": "三星",
    "model_name_model": "Galaxy S8+"
  },
  {
    "model_manuf": "Samsung",
    "model_model": "SM-N9300",
    "model_name_manuf": "三星",
    "model_name_model": "Galaxy Note 7"
  },
  {
    "model_manuf": "Samsung",
    "model_model": "SM-W2017 ",
    "model_name_manuf": "三星",
    "model_name_model": "Galaxy C7"
  },
  {
    "model_manuf": "Samsung",
    "model_model": "SM-G5520",
    "model_name_manuf": "三星",
    "model_name_model": "Galaxy ON5"
  },
  {
    "model_manuf": "Samsung",
    "model_model": "SM-G5520",
    "model_name_manuf": "三星",
    "model_name_model": "Galaxy ON5"
  },
  {
    "model_manuf": "Samsung",
    "model_model": "SM-C9000",
    "model_name_manuf": "三星",
    "model_name_model": "Galaxy C9 Pro"
  },
  {
    "model_manuf": "Sony",
    "model_model": "L55t",
    "model_name_manuf": "索尼",
    "model_name_model": "Xperia Z3"
  },
  {
    "model_manuf": "Sony",
    "model_model": "E6883",
    "model_name_manuf": "索尼",
    "model_name_model": "Xperia Z5 Premium"
  },
  {
    "model_manuf": "Sony",
    "model_model": "E6683",
    "model_name_manuf": "索尼",
    "model_name_model": "Xperia Z5"
  },
  {
    "model_manuf": "Sony",
    "model_model": "E6533",
    "model_name_manuf": "索尼",
    "model_name_model": "Xperia Z3+"
  },
  {
    "model_manuf": "Sony",
    "model_model": "F8132",
    "model_name_manuf": "索尼",
    "model_name_model": "Xperia X Performance"
  },
  {
    "model_manuf": "Sony",
    "model_model": "G8231",
    "model_name_manuf": "索尼",
    "model_name_model": "Xperia XZs"
  },
  {
    "model_manuf": "Sony",
    "model_model": "G8141",
    "model_name_manuf": "索尼",
    "model_name_model": "Xperia XZ Premium"
  },
  {
    "model_manuf": "Sony",
    "model_model": "G3312",
    "model_name_manuf": "索尼",
    "model_name_model": "Xperia L1"
  },
  {
    "model_manuf": "OPPO",
    "model_model": "PBEM00",
    "model_name_manuf": "OPPO",
    "model_name_model": "OPPO R17"
  },
  {
    "model_manuf": "OPPO",
    "model_model": "PAFM00",
    "model_name_manuf": "OPPO",
    "model_name_model": "OPPO FindX兰博基尼版"
  },
  {
    "model_manuf": "HUAWEI",
    "model_model": "RVL-AL09",
    "model_name_manuf": "华为",
    "model_name_model": "荣耀Note10"
  },
  {
    "model_manuf": "Meizu",
    "model_model": "Meizu 16th/16th Plus",
    "model_name_manuf": "魅族",
    "model_name_model": "魅族16旗舰手机"
  },
  {
    "model_manuf": "vivo",
    "model_model": "EXP1831",
    "model_name_manuf": "vivo/IQOO",
    "model_name_model": "vivo APEX 2019"
  },
  {
    "model_manuf": "Xiaomi",
    "model_model": "21121210C",
    "model_name_manuf": "小米/红米",
    "model_name_model": "Redmi K50 电竞版"
  },
  {
    "model_manuf": "Xiaomi",
    "model_model": "22011211C",
    "model_name_manuf": "小米/红米",
    "model_name_model": "Redmi K50 Pro"
  },
  {
    "model_manuf": "Xiaomi",
    "model_model": "22041211AC",
    "model_name_manuf": "小米/红米",
    "model_name_model": "Redmi K50"
  },
  {
    "model_manuf": "Xiaomi",
    "model_model": "22021211RC",
    "model_name_manuf": "小米/红米",
    "model_name_model": "Redmi K40S"
  },
  {
    "model_manuf": "realme",
    "model_model": "RMX3560",
    "model_name_manuf": "realme",
    "model_name_model": "真我 GT Neo3"
  },
  {
    "model_manuf": "realme",
    "model_model": "RMX3562",
    "model_name_manuf": "realme",
    "model_name_model": "真我 GT Neo3 150W"
  },
  {
    "model_manuf": "realme",
    "model_model": "RMX3300",
    "model_name_manuf": "realme",
    "model_name_model": "真我 GT2 Pro"
  },
  {
    "model_manuf": "realme",
    "model_model": "RMX3478",
    "model_name_manuf": "真我",
    "model_name_model": "真我 Q5"
  },
  {
    "model_manuf": "realme",
    "model_model": "RMX3372",
    "model_name_manuf": "真我",
    "model_name_model": "真我 Q5 Pro"
  },
  {
    "model_manuf": "realme",
    "model_model": "RMX3574",
    "model_name_manuf": "真我",
    "model_name_model": "真我 Q5i"
  },
  {
    "model_manuf": "realme",
    "model_model": "RMX2117",
    "model_name_manuf": "真我",
    "model_name_model": "真我 Q2"
  },
  {
    "model_manuf": "realme",
    "model_model": "RMX3357",
    "model_name_manuf": "realme",
    "model_name_model": "真我 GT Neo2 T"
  },
  {
    "model_manuf": "realme",
    "model_model": "RMX3310",
    "model_name_manuf": "realme",
    "model_name_model": "真我 GT2"
  },
  {
    "model_manuf": "realme",
    "model_model": "RMX3461",
    "model_name_manuf": "realme",
    "model_name_model": "真我 Q3s"
  },
  {
    "model_manuf": "realme",
    "model_model": "RMX3370",
    "model_name_manuf": "realme",
    "model_name_model": "真我 GT Neo2"
  },
  {
    "model_manuf": "realme",
    "model_model": "RMX3125",
    "model_name_manuf": "realme",
    "model_name_model": "真我 V11s"
  },
  {
    "model_manuf": "realme",
    "model_model": "RMX3571",
    "model_name_manuf": "真我",
    "model_name_model": "真我 V23"
  },
  {
    "model_manuf": "realme",
    "model_model": "RMX3366",
    "model_name_manuf": "realme",
    "model_name_model": "真我 V25"
  },
  {
    "model_manuf": "realme",
    "model_model": "RMX3475",
    "model_name_manuf": "realme",
    "model_name_model": "真我 GT 大师探索版"
  },
  {
    "model_manuf": "realme",
    "model_model": "RMX3361",
    "model_name_manuf": "realme",
    "model_name_model": "真我 GT 大师版"
  },
  {
    "model_manuf": "realme",
    "model_model": "RMX3350",
    "model_name_manuf": "realme",
    "model_name_model": "真我 GT Neo闪速版"
  },
  {
    "model_manuf": "realme",
    "model_model": "RMX3142",
    "model_name_manuf": "realme",
    "model_name_model": "真我 Q3 Pro 狂欢版"
  },
  {
    "model_manuf": "realme",
    "model_model": "RMX3042",
    "model_name_manuf": "realme",
    "model_name_model": "真我 Q3i"
  },
  {
    "model_manuf": "realme",
    "model_model": "RMX3161",
    "model_name_manuf": "realme",
    "model_name_model": "真我 Q3"
  },
  {
    "model_manuf": "realme",
    "model_model": "RMX2205",
    "model_name_manuf": "realme",
    "model_name_model": "真我 Q3 Pro"
  },
  {
    "model_manuf": "realme",
    "model_model": "RMX3115",
    "model_name_manuf": "realme",
    "model_name_model": "真我 X7 Pro 至尊版"
  },
  {
    "model_manuf": "realme",
    "model_model": "RMX3031",
    "model_name_manuf": "realme",
    "model_name_model": "真我 GT Neo"
  },
  {
    "model_manuf": "realme",
    "model_model": "RMX3043",
    "model_name_manuf": "realme",
    "model_name_model": "真我 V13"
  },
  {
    "model_manuf": "realme",
    "model_model": "RMX2202",
    "model_name_manuf": "realme",
    "model_name_model": "真我 GT"
  },
  {
    "model_manuf": "realme",
    "model_model": "RMX3121",
    "model_name_manuf": "realme",
    "model_name_model": "真我 V11"
  },
  {
    "model_manuf": "realme",
    "model_model": "RMX3092",
    "model_name_manuf": "realme",
    "model_name_model": "真我 V15"
  },
  {
    "model_manuf": "BlackShark",
    "model_model": "MBU-A0",
    "model_name_manuf": "黑鲨",
    "model_name_model": "黑鲨 3 Pro"
  },
  {
    "model_manuf": "BlackShark",
    "model_model": "KLE-A0",
    "model_name_manuf": "黑鲨",
    "model_name_model": "黑鲨 3 "
  },
  {
    "model_manuf": "BlackShark",
    "model_model": "KLE-A0",
    "model_name_manuf": "黑鲨",
    "model_name_model": "黑鲨 3s"
  },
  {
    "model_manuf": "BlackShark",
    "model_model": "PRS-A0",
    "model_name_manuf": "黑鲨",
    "model_name_model": "黑鲨 4"
  },
  {
    "model_manuf": "BlackShark",
    "model_model": "KSR-A0",
    "model_name_manuf": "黑鲨",
    "model_name_model": "黑鲨 4 Pro"
  },
  {
    "model_manuf": "BlackShark",
    "model_model": "",
    "model_name_manuf": "黑鲨",
    "model_name_model": "黑鲨4s型号为4的4spro为4pro的"
  },
  {
    "model_manuf": "BlackShark",
    "model_model": "KSR-A0",
    "model_name_manuf": "黑鲨",
    "model_name_model": "黑鲨5RS是黑鲨4Pro的"
  },
  {
    "model_manuf": "BlackShark",
    "model_model": "KTUS-A0",
    "model_name_manuf": "黑鲨",
    "model_name_model": "黑鲨5 Pro"
  },
  {
    "model_manuf": "BlackShark",
    "model_model": "PAR-A0",
    "model_name_manuf": "黑鲨",
    "model_name_model": "黑鲨5"
  },
  {
    "model_manuf": "Everest",
    "model_model": "8848 M6",
    "model_name_manuf": "8848",
    "model_name_model": "8848 M6"
  },
  {
    "model_manuf": "vivo",
    "model_model": "V2172A",
    "model_name_manuf": "vivo/IQOO",
    "model_name_model": "IQOO 9 Pro"
  },
  {
    "model_manuf": "vivo",
    "model_model": "V2171A",
    "model_name_manuf": "vivo/IQOO",
    "model_name_model": "IQOO 9"
  },
  {
    "model_manuf": "vivo",
    "model_model": "V2141A",
    "model_name_manuf": "vivo/IQOO",
    "model_name_model": "IQOO 8 Pro"
  },
  {
    "model_manuf": "vivo",
    "model_model": "V2136A",
    "model_name_manuf": "vivo/IQOO",
    "model_name_model": "IQOO 8"
  },
  {
    "model_manuf": "vivo",
    "model_model": "V2196A",
    "model_name_manuf": "vivo/IQOO",
    "model_name_model": "IQOO Neo6"
  },
  {
    "model_manuf": "vivo",
    "model_model": "V2154A",
    "model_name_manuf": "vivo/IQOO",
    "model_name_model": "IQOO Neo5S"
  },
  {
    "model_manuf": "vivo",
    "model_model": "V2055A",
    "model_name_manuf": "vivo/IQOO",
    "model_name_model": "IQOO Neo5"
  },
  {
    "model_manuf": "vivo",
    "model_model": "V2157A",
    "model_name_manuf": "vivo/IQOO",
    "model_name_model": "IQOO Neo5 SE"
  },
  {
    "model_manuf": "vivo",
    "model_model": "V2118A",
    "model_name_manuf": "vivo/IQOO",
    "model_name_model": "IQOO Neo5 活力版"
  },
  {
    "model_manuf": "vivo",
    "model_model": "V2049A",
    "model_name_manuf": "vivo/IQOO",
    "model_name_model": "IQOO 7"
  },
  {
    "model_manuf": "vivo",
    "model_model": "V2048A",
    "model_name_manuf": "vivo/IQOO",
    "model_name_model": "IQOO Z5"
  },
  {
    "model_manuf": "vivo",
    "model_model": "V2131A",
    "model_name_manuf": "vivo/IQOO",
    "model_name_model": "IQOO Z5x"
  },
  {
    "model_manuf": "vivo",
    "model_model": "V2025A",
    "model_name_manuf": "vivo/IQOO",
    "model_name_model": "IQOO 5 Pro"
  },
  {
    "model_manuf": "vivo",
    "model_model": "V2024A",
    "model_name_manuf": "vivo/IQOO",
    "model_name_model": "IQOO 5"
  },
  {
    "model_manuf": "vivo",
    "model_model": "V2073A",
    "model_name_manuf": "vivo/IQOO",
    "model_name_model": "IQOO Z3"
  },
  {
    "model_manuf": "vivo",
    "model_model": "V2012A",
    "model_name_manuf": "vivo/IQOO",
    "model_name_model": "IQOO Z1x"
  },
  {
    "model_manuf": "vivo",
    "model_model": "V1986A",
    "model_name_manuf": "vivo/IQOO",
    "model_name_model": "IQOO Z1"
  },
  {
    "model_manuf": "vivo",
    "model_model": "V1981A",
    "model_name_manuf": "vivo/IQOO",
    "model_name_model": "IQOO Neo3"
  },
  {
    "model_manuf": "vivo",
    "model_model": "V2165A",
    "model_name_manuf": "vivo/IQOO",
    "model_name_model": "IQOO U5"
  },
  {
    "model_manuf": "vivo",
    "model_model": "V2061A",
    "model_name_manuf": "vivo/IQOO",
    "model_name_model": "IQOO U3"
  },
  {
    "model_manuf": "vivo",
    "model_model": "V2106A",
    "model_name_manuf": "vivo/IQOO",
    "model_name_model": "IQOO U3x"
  },
  {
    "model_manuf": "vivo",
    "model_model": "V2023A",
    "model_name_manuf": "vivo/IQOO",
    "model_name_model": "IQOO U1"
  },
  {
    "model_manuf": "vivo",
    "model_model": "V1955A",
    "model_name_manuf": "vivo/IQOO",
    "model_name_model": "IQOO 3"
  },
  {
    "model_manuf": "vivo",
    "model_model": "V1936AL",
    "model_name_manuf": "vivo/IQOO",
    "model_name_model": "IQOO Neo 855 竞速版"
  },
  {
    "model_manuf": "vivo",
    "model_model": "V1936A",
    "model_name_manuf": "vivo/IQOO",
    "model_name_model": "IQOO Neo 855"
  },
  {
    "model_manuf": "vivo",
    "model_model": "V1916A",
    "model_name_manuf": "vivo/IQOO",
    "model_name_model": "IQOO Pro 5G"
  },
  {
    "model_manuf": "vivo",
    "model_model": "V1914A",
    "model_name_manuf": "vivo/IQOO",
    "model_name_model": "IQOO Neo"
  },
  {
    "model_manuf": "Xiaomi",
    "model_model": "2201122C",
    "model_name_manuf": "小米/红米",
    "model_name_model": "小米 12 Pro"
  },
  {
    "model_manuf": "Xiaomi",
    "model_model": "2201123C",
    "model_name_manuf": "小米/红米",
    "model_name_model": "小米 12"
  },
  {
    "model_manuf": "Xiaomi",
    "model_model": "2201123AC",
    "model_name_manuf": "小米/红米",
    "model_name_model": "小米 12X"
  },
  {
    "model_manuf": "Xiaomi",
    "model_model": "2109116UC",
    "model_name_manuf": "小米/红米",
    "model_name_model": "Redmi Note11 Pro+"
  },
  {
    "model_manuf": "Xiaomi",
    "model_model": "2019116C",
    "model_name_manuf": "小米/红米",
    "model_name_model": "Redmi Note11E Pro"
  },
  {
    "model_manuf": "Xiaomi",
    "model_model": "2201116SC",
    "model_name_manuf": "小米/红米",
    "model_name_model": "Redmi Note11 Pro"
  },
  {
    "model_manuf": "Xiaomi",
    "model_model": "2109116AC",
    "model_name_manuf": "小米/红米",
    "model_name_model": "Redmi Note11"
  },
  {
    "model_manuf": "Xiaomi",
    "model_model": "2109119B",
    "model_name_manuf": "小米/红米",
    "model_name_model": "小米 Civi"
  },
  {
    "model_manuf": "Xiaomi",
    "model_model": "2109119BC",
    "model_name_manuf": "小米/红米",
    "model_name_model": "小米 Civi 1S"
  },
  {
    "model_manuf": "Xiaomi",
    "model_model": "21051182C",
    "model_name_manuf": "小米/红米",
    "model_name_model": "小米平板5 Pro   5G"
  },
  {
    "model_manuf": "Xiaomi",
    "model_model": "M2105K81AC",
    "model_name_manuf": "小米/红米",
    "model_name_model": "小米平板5 Pro   WIFI"
  },
  {
    "model_manuf": "Xiaomi",
    "model_model": "21051182C",
    "model_name_manuf": "小米/红米",
    "model_name_model": "小米平板5"
  },
  {
    "model_manuf": "Xiaomi",
    "model_model": "2106118C",
    "model_name_manuf": "小米/红米",
    "model_name_model": "小米 MIX4"
  },
  {
    "model_manuf": "Xiaomi",
    "model_model": "M2014K10AC",
    "model_name_manuf": "小米/红米",
    "model_name_model": "Redmi Note10 Pro"
  },
  {
    "model_manuf": "Xiaomi",
    "model_model": "M2013K19C",
    "model_name_manuf": "小米/红米",
    "model_name_model": "Redmi Note10"
  },
  {
    "model_manuf": "Xiaomi",
    "model_model": "M2102K1C",
    "model_name_manuf": "小米/红米",
    "model_name_model": "小米 11 Ultra"
  },
  {
    "model_manuf": "Xiaomi",
    "model_model": "M2102K1AC",
    "model_name_manuf": "小米/红米",
    "model_name_model": "小米 11 Pro"
  },
  {
    "model_manuf": "Xiaomi",
    "model_model": "M2011K2C",
    "model_name_manuf": "小米/红米",
    "model_name_model": "小米 11"
  },
  {
    "model_manuf": "Xiaomi",
    "model_model": "M2101K9C",
    "model_name_manuf": "小米/红米",
    "model_name_model": "小米 11 青春版"
  },
  {
    "model_manuf": "Xiaomi",
    "model_model": "M2012K11C",
    "model_name_manuf": "小米/红米",
    "model_name_model": "Redmi K40 Pro"
  },
  {
    "model_manuf": "Xiaomi",
    "model_model": "M2012K11AC",
    "model_name_manuf": "小米/红米",
    "model_name_model": "Redmi K40"
  },
  {
    "model_manuf": "Xiaomi",
    "model_model": "M2012K10C",
    "model_name_manuf": "小米/红米",
    "model_name_model": "Redmi K40 游戏增强版"
  },
  {
    "model_manuf": "Xiaomi",
    "model_model": "M2011J18C",
    "model_name_manuf": "小米/红米",
    "model_name_model": "小米 MIX Fold"
  },
  {
    "model_manuf": "Xiaomi",
    "model_model": "M2102J2SC",
    "model_name_manuf": "小米/红米",
    "model_name_model": "小米 10S"
  },
  {
    "model_manuf": "Xiaomi",
    "model_model": "M2007J17C",
    "model_name_manuf": "小米/红米",
    "model_name_model": "Redmi Note9 Pro"
  },
  {
    "model_manuf": "Xiaomi",
    "model_model": "M2007J22C",
    "model_name_manuf": "小米/红米",
    "model_name_model": "Redmi Note9 5G"
  },
  {
    "model_manuf": "Xiaomi",
    "model_model": "M2010J19SC",
    "model_name_manuf": "小米/红米",
    "model_name_model": "Redmi Note9 4G"
  },
  {
    "model_manuf": "Xiaomi",
    "model_model": "M2007J3SC",
    "model_name_manuf": "小米/红米",
    "model_name_model": "Redmi K30S Ultra"
  },
  {
    "model_manuf": "Xiaomi",
    "model_model": "M2006J10C",
    "model_name_manuf": "小米/红米",
    "model_name_model": "Redmi K30 Ultra"
  },
  {
    "model_manuf": "Xiaomi",
    "model_model": "M2001J11C",
    "model_name_manuf": "小米/红米",
    "model_name_model": "Redmi K30 Pro"
  },
  {
    "model_manuf": "Xiaomi",
    "model_model": "M2001G7AC",
    "model_name_manuf": "小米/红米",
    "model_name_model": "Redmi K30"
  },
  {
    "model_manuf": "Xiaomi",
    "model_model": "M2007J1SC",
    "model_name_manuf": "小米/红米",
    "model_name_model": "小米 10 Ultra"
  },
  {
    "model_manuf": "Xiaomi",
    "model_model": "M200J1C",
    "model_name_manuf": "小米/红米",
    "model_name_model": "小米 10 Pro"
  },
  {
    "model_manuf": "Xiaomi",
    "model_model": "M200J2C",
    "model_name_manuf": "小米/红米",
    "model_name_model": "小米 10"
  },
  {
    "model_manuf": "Xiaomi",
    "model_model": "M2004J7BC",
    "model_name_manuf": "小米/红米",
    "model_name_model": "Redmi 10X Pro"
  },
  {
    "model_manuf": "Xiaomi",
    "model_model": "M2004J7AC",
    "model_name_manuf": "小米/红米",
    "model_name_model": "Redmi 10X 5G"
  },
  {
    "model_manuf": "Xiaomi",
    "model_model": "M2003J15SC",
    "model_name_manuf": "小米/红米",
    "model_name_model": "Redmi 10X 4G"
  },
  {
    "model_manuf": "Xiaomi",
    "model_model": "M2004J19C",
    "model_name_manuf": "小米/红米",
    "model_name_model": "Redmi 9"
  },
  {
    "model_manuf": "Xiaomi",
    "model_model": "M2006C3LC",
    "model_name_manuf": "小米/红米",
    "model_name_model": "Redmi 9A"
  },
  {
    "model_manuf": "Xiaomi",
    "model_model": "MI 2S",
    "model_name_manuf": "小米/红米",
    "model_name_model": "小米2S"
  },
  {
    "model_manuf": "Xiaomi",
    "model_model": "MI 3",
    "model_name_manuf": "小米/红米",
    "model_name_model": "小米3"
  },
  {
    "model_manuf": "Xiaomi",
    "model_model": "MI 4LTE",
    "model_name_manuf": "小米/红米",
    "model_name_model": "小米4"
  },
  {
    "model_manuf": "Xiaomi",
    "model_model": "MI-4C",
    "model_name_manuf": "小米/红米",
    "model_name_model": "小米4C"
  },
  {
    "model_manuf": "Xiaomi",
    "model_model": "MI 4S",
    "model_name_manuf": "小米/红米",
    "model_name_model": "小米4S"
  },
  {
    "model_manuf": "Xiaomi",
    "model_model": "MI 5",
    "model_name_manuf": "小米/红米",
    "model_name_model": "小米5"
  },
  {
    "model_manuf": "Xiaomi",
    "model_model": "MI NOTE LTE",
    "model_name_manuf": "小米/红米",
    "model_name_model": "小米NOTE"
  },
  {
    "model_manuf": "Xiaomi",
    "model_model": "MI MAX",
    "model_name_manuf": "小米/红米",
    "model_name_model": "小米MAX"
  },
  {
    "model_manuf": "Xiaomi",
    "model_model": "MI NOTE 2",
    "model_name_manuf": "小米/红米",
    "model_name_model": "小米NOTE 2"
  },
  {
    "model_manuf": "Xiaomi",
    "model_model": "MI NOTE PRO",
    "model_name_manuf": "小米/红米",
    "model_name_model": "小米NOTE 顶配版"
  },
  {
    "model_manuf": "Xiaomi",
    "model_model": "Redmi Note 3",
    "model_name_manuf": "小米/红米",
    "model_name_model": "红米Note3"
  },
  {
    "model_manuf": "Xiaomi",
    "model_model": "MI Pad 2",
    "model_name_manuf": "小米/红米",
    "model_name_model": "小米平板2"
  },
  {
    "model_manuf": "Xiaomi",
    "model_model": "2016080 ",
    "model_name_manuf": "小米/红米",
    "model_name_model": "小米5S"
  },
  {
    "model_manuf": "Xiaomi",
    "model_model": "2016060",
    "model_name_manuf": "小米/红米",
    "model_name_model": "小米 Note 4"
  },
  {
    "model_manuf": "Xiaomi",
    "model_model": "MIX",
    "model_name_manuf": "小米/红米",
    "model_name_model": "小米MIX"
  },
  {
    "model_manuf": "Xiaomi",
    "model_model": "MI MIX2S Emerald Edition",
    "model_name_manuf": "小米/红米",
    "model_name_model": "小米MIX2S 翡翠艺术版"
  },
  {
    "model_manuf": "vivo",
    "model_model": "PA2170",
    "model_name_manuf": "vivo/IQOO",
    "model_name_model": "vivo Pad"
  },
  {
    "model_manuf": "vivo",
    "model_model": "V2178A",
    "model_name_manuf": "vivo/IQOO",
    "model_name_model": "vivo X Fold"
  },
  {
    "model_manuf": "vivo",
    "model_model": "V2170A",
    "model_name_manuf": "vivo/IQOO",
    "model_name_model": "vivo X Note"
  },
  {
    "model_manuf": "vivo",
    "model_model": "V2185A",
    "model_name_manuf": "vivo/IQOO",
    "model_name_model": "vivo X80 Pro 骁龙版"
  },
  {
    "model_manuf": "vivo",
    "model_model": "V2186A",
    "model_name_manuf": "vivo/IQOO",
    "model_name_model": "vivo X80 Pro 天玑版"
  },
  {
    "model_manuf": "vivo",
    "model_model": "V2145A",
    "model_name_manuf": "vivo/IQOO",
    "model_name_model": "vivo X70 Pro+"
  },
  {
    "model_manuf": "vivo",
    "model_model": "V2134A",
    "model_name_manuf": "vivo/IQOO",
    "model_name_model": "vivo X70 Pro"
  },
  {
    "model_manuf": "vivo",
    "model_model": "V2133A",
    "model_name_manuf": "vivo/IQOO",
    "model_name_model": "vivo X70"
  },
  {
    "model_manuf": "vivo",
    "model_model": "V2056A",
    "model_name_manuf": "vivo/IQOO",
    "model_name_model": "vivo X60 Pro+"
  },
  {
    "model_manuf": "vivo",
    "model_model": "V2047A",
    "model_name_manuf": "vivo/IQOO",
    "model_name_model": "vivo X60 Pro"
  },
  {
    "model_manuf": "vivo",
    "model_model": "V2046A",
    "model_name_manuf": "vivo/IQOO",
    "model_name_model": "vivo X60"
  },
  {
    "model_manuf": "vivo",
    "model_model": "V2059A",
    "model_name_manuf": "vivo/IQOO",
    "model_name_model": "vivo X60曲屏版"
  },
  {
    "model_manuf": "vivo",
    "model_model": "V2011A",
    "model_name_manuf": "vivo/IQOO",
    "model_name_model": "vivo X50 Pro+"
  },
  {
    "model_manuf": "vivo",
    "model_model": "V2005A",
    "model_name_manuf": "vivo/IQOO",
    "model_name_model": "vivo X50 Pro"
  },
  {
    "model_manuf": "vivo",
    "model_model": "V2001A",
    "model_name_manuf": "vivo/IQOO",
    "model_name_model": "vivo X50"
  },
  {
    "model_manuf": "vivo",
    "model_model": "V1938T",
    "model_name_manuf": "vivo/IQOO",
    "model_name_model": "vivo X30 Pro"
  },
  {
    "model_manuf": "vivo",
    "model_model": "V1938A",
    "model_name_manuf": "vivo/IQOO",
    "model_name_model": "vivo X30"
  },
  {
    "model_manuf": "vivo",
    "model_model": "V2166A",
    "model_name_manuf": "vivo/IQOO",
    "model_name_model": "vivo Y33s"
  },
  {
    "model_manuf": "vivo",
    "model_model": "V2199A",
    "model_name_manuf": "vivo/IQOO",
    "model_name_model": "vivo S15"
  },
  {
    "model_manuf": "vivo",
    "model_model": "V2190A",
    "model_name_manuf": "vivo/IQOO",
    "model_name_model": "vivo S13e"
  },
  {
    "model_manuf": "vivo",
    "model_model": "V2163A",
    "model_name_manuf": "vivo/IQOO",
    "model_name_model": "vivo S12 Pro"
  },
  {
    "model_manuf": "vivo",
    "model_model": "V2162A",
    "model_name_manuf": "vivo/IQOO",
    "model_name_model": "vivo S12"
  },
  {
    "model_manuf": "vivo",
    "model_model": "V2121A",
    "model_name_manuf": "vivo/IQOO",
    "model_name_model": "vivo S10/vivo S10 Pro"
  },
  {
    "model_manuf": "vivo",
    "model_model": "V2072A",
    "model_name_manuf": "vivo/IQOO",
    "model_name_model": "vivo S9"
  },
  {
    "model_manuf": "Sony",
    "model_model": "XQ-BE72",
    "model_name_manuf": "索尼",
    "model_name_model": "索尼 Xperia Pro I"
  },
  {
    "model_manuf": "Sony",
    "model_model": "XQ-BQ72",
    "model_name_manuf": "索尼",
    "model_name_model": "索尼 Xperia5 III"
  },
  {
    "model_manuf": "Sony",
    "model_model": "XQ-BC72",
    "model_name_manuf": "索尼",
    "model_name_model": "索尼 Xperia1 III"
  },
  {
    "model_manuf": "Motorola",
    "model_model": "XT2175-2",
    "model_name_manuf": "摩托罗拉",
    "model_name_model": "Motorola edge S30"
  },
  {
    "model_manuf": "Motorola",
    "model_model": "XT2201-6",
    "model_name_manuf": "摩托罗拉",
    "model_name_model": "Motorola edge X30 屏下版"
  },
  {
    "model_manuf": "Motorola",
    "model_model": "XT2201-2",
    "model_name_manuf": "摩托罗拉",
    "model_name_model": "Motorola edge X30"
  },
  {
    "model_manuf": "Motorola",
    "model_model": "XT2153-1",
    "model_name_manuf": "摩托罗拉",
    "model_name_model": "Motorola edge S Pro"
  },
  {
    "model_manuf": "Motorola",
    "model_model": "XT2125-4",
    "model_name_manuf": "摩托罗拉",
    "model_name_model": "Motorola edge S"
  },
  {
    "model_manuf": "Motorola",
    "model_model": "XT2143-1",
    "model_name_manuf": "摩托罗拉",
    "model_name_model": "Motorola edge 轻奢版"
  },
  {
    "model_manuf": "OnePlus",
    "model_model": "PGKM10",
    "model_name_manuf": "一加",
    "model_name_model": "OnePlus Ace"
  },
  {
    "model_manuf": "OnePlus",
    "model_model": "NE2210",
    "model_name_manuf": "一加",
    "model_name_model": "OnePlus 10 Pro"
  },
  {
    "model_manuf": "OnePlus",
    "model_model": "LE2120",
    "model_name_manuf": "一加",
    "model_name_model": "OnePlus 9 Pro"
  },
  {
    "model_manuf": "OnePlus",
    "model_model": "LE2110",
    "model_name_manuf": "一加",
    "model_name_model": "OnePlus 9"
  },
  {
    "model_manuf": "OnePlus",
    "model_model": "MT2110",
    "model_name_manuf": "一加",
    "model_name_model": "OnePlus 9 RT"
  },
  {
    "model_manuf": "OnePlus",
    "model_model": "LE2100",
    "model_name_manuf": "一加",
    "model_name_model": "OnePlus 9 R"
  },
  {
    "model_manuf": "OnePlus",
    "model_model": "IN2020",
    "model_name_manuf": "一加",
    "model_name_model": "OnePlus 8 Pro"
  },
  {
    "model_manuf": "OnePlus",
    "model_model": "KB2000",
    "model_name_manuf": "一加",
    "model_name_model": "OnePlus 8 T"
  },
  {
    "model_manuf": "OnePlus",
    "model_model": "IN2010",
    "model_name_manuf": "一加",
    "model_name_model": "OnePlus 8"
  },
  {
    "model_manuf": "OnePlus",
    "model_model": "HD1910",
    "model_name_manuf": "一加",
    "model_name_model": "OnePlus 7 T Pro"
  },
  {
    "model_manuf": "OnePlus",
    "model_model": "GM1910",
    "model_name_manuf": "一加",
    "model_name_model": "OnePlus 7 Pro"
  },
  {
    "model_manuf": "OnePlus",
    "model_model": "HD1900",
    "model_name_manuf": "一加",
    "model_name_model": "OnePlus 7 T"
  },
  {
    "model_manuf": "OnePlus",
    "model_model": "GM1900",
    "model_name_manuf": "一加",
    "model_name_model": "OnePlus 7"
  }
]